composerml/__init__.py
composerml/models/__init__.py
composerml/models/layer.py
composerml/models/mlpmusicgen.py
composerml/models/mlpnetwork.py
composerml/models/neuron.py
composerml/models/trainedmusicgen.py
composerml/models/value.py
composerml/music_generation/__init__.py
composerml/music_generation/analysis.py
composerml/music_generation/midi_to_dataset.py
composerml/music_generation/music_dataset.py
composerml/music_generation/play_song.py
composerml/training/__init__.py
composerml/training/evaluator.py
composerml/training/musictrainer.py
composerml/training/trainer.py
composerml/training/losses/__init__.py
composerml/training/losses/bce_loss.py
composerml/training/losses/ce_loss.py
composerml/training/losses/linear_loss.py
composerml/training/losses/loss.py
composerml/training/optimizer/SGD.py
composerml/training/optimizer/__init__.py
composerml/training/optimizer/op.py
composerml-0.1.0.dist-info/METADATA
composerml-0.1.0.dist-info/WHEEL
composerml-0.1.0.dist-info/top_level.txt
composerml-0.1.0.dist-info/RECORD
