Metadata-Version: 2.4
Name: composerml
Version: 0.1.0
Summary: A simple music generation library using Karpathy's autograd network
Author: Peter Nguyen
Requires-Dist: numpy
Requires-Dist: pandas
Requires-Dist: mido
Requires-Dist: pygame
